fias_public_api/__init__.py
fias_public_api/constants.py
fias_public_api/fias_async.py
fias_public_api/fias_sync.py
fias_public_api-1.0.3.dist-info/METADATA
fias_public_api-1.0.3.dist-info/WHEEL
fias_public_api-1.0.3.dist-info/licenses/LICENSE
fias_public_api-1.0.3.dist-info/RECORD
