Metadata-Version: 2.4
Name: fias-public-api
Version: 1.0.3
Summary: Python client for FIAS Public API - Russian address database
Project-URL: Homepage, https://github.com/quonaro/fias-public-api
Project-URL: Repository, https://github.com/quonaro/fias-public-api
Project-URL: Documentation, https://github.com/quonaro/fias-public-api#readme
Project-URL: Issues, https://github.com/quonaro/fias-public-api/issues
Author-email: quonaro <quonaro@mail.ru>
License: MIT
License-File: LICENSE
Keywords: address,api,fias,nalog,russia
Classifier: Development Status :: 4 - Beta
Classifier: Intended Audience :: Developers
Classifier: License :: OSI Approved :: MIT License
Classifier: Programming Language :: Python :: 3
Classifier: Programming Language :: Python :: 3.12
Classifier: Programming Language :: Python :: 3.13
Classifier: Topic :: Internet :: WWW/HTTP :: Dynamic Content
Classifier: Topic :: Software Development :: Libraries :: Python Modules
Requires-Python: >=3.12
Requires-Dist: httpx>=0.28.1
Requires-Dist: requests>=2.32.5
